{
  "CITY": "fr_City",
  "COUNTRY": "fr_Country",
  "PROVINCE": "fr_Province",
  "POSTAL": "fr_Postal Code",
  "PROVSTATE": "fr_Province or State",
  "STATE": "fr_State",
  "STREET": "fr_Street Address",
  "ZIP": "fr_Zip Code",
  "COMPANYNAME_FULL": "fr_Full Company Name",
  "COMPANY": "fr_Company",
  "ADD_ADDRESS": "fr_Add Address",
  "CITY_TOWN": "City or Town",
  "SAVE_ADDR": "Save Address",
  "DELETE_ADDR": "Delete Address",
  "ADDR_INFO": "fr_Address Information",
  "ADDR_DETAILS": "fr_Address Details"
}